candycan/__init__.py
candycan/_modidx.py
candycan/a2l.py
candycan/core.py
candycan/dbc.py
candycan/receive_message.py
candycan/send_message.py
candycan/xcp.py
candycan/ccp/__init__.py
candycan/ccp/scapy.py
candycan/ccp/socketcan.py
candycan/ccp/virtual.py
candycan/data_link/__init__.py
candycan/data_link/scapycan.py
candycan/data_link/socketcan.py
candycan-0.0.1.dist-info/LICENSE
candycan-0.0.1.dist-info/METADATA
candycan-0.0.1.dist-info/WHEEL
candycan-0.0.1.dist-info/entry_points.txt
candycan-0.0.1.dist-info/top_level.txt
candycan-0.0.1.dist-info/RECORD
