Metadata-Version: 2.1
Name: candycan
Version: 0.0.1
Summary: can wrapper for applications
Home-page: https://github.com/Binjian/candycan
Author: binjian xin
Author-email: binjian.xin@hotmail.com
License: Apache Software License 2.0
Keywords: nbdev jupyter notebook python
Classifier: Development Status :: 4 - Beta
Classifier: Intended Audience :: Developers
Classifier: Natural Language :: English
Classifier: Programming Language :: Python :: 3.11
Classifier: License :: OSI Approved :: Apache Software License
Requires-Python: >=3.11
License-File: LICENSE
Requires-Dist: fastcore
Requires-Dist: pandas
Requires-Dist: ijson
Requires-Dist: gitpython
Requires-Dist: typing-inspect
Requires-Dist: typeguard
Requires-Dist: numpy
Requires-Dist: seaborn
Requires-Dist: scikit-learn
Requires-Dist: python-can
Requires-Dist: cantools
Requires-Dist: dbc-editor
Requires-Dist: scapy
Requires-Dist: pyx
Requires-Dist: InquirerPy
Requires-Dist: pydantic
Requires-Dist: mypy
Requires-Dist: pylint
Requires-Dist: black[jupyter]
Provides-Extra: dev
